stagekit/__init__.py
stagekit/context.py
stagekit/directory.py
stagekit/root.py
stagekit/schedule.py
stagekit/stage.py
stagekit-0.0.2.dist-info/METADATA
stagekit-0.0.2.dist-info/WHEEL
stagekit-0.0.2.dist-info/top_level.txt
stagekit-0.0.2.dist-info/RECORD
